bluemvmt_gsf/__init__.py
bluemvmt_gsf/models/__init__.py
bluemvmt_gsf/models/gsf_sensor_specific.py
bluemvmt_gsf/reader/__init__.py
bluemvmt_gsf/reader/gsf3_09.py
bluemvmt_gsf-0.1.0.dist-info/LICENSE.txt
bluemvmt_gsf-0.1.0.dist-info/METADATA
bluemvmt_gsf-0.1.0.dist-info/WHEEL
bluemvmt_gsf-0.1.0.dist-info/top_level.txt
bluemvmt_gsf-0.1.0.dist-info/RECORD
