Metadata-Version: 2.1
Name: bluemvmt-gsf
Version: 0.1.0
Summary: Add a short description here!
Home-page: https://github.com/pyscaffold/pyscaffold/
Author: Vincent Sheffer
Author-email: vincent.sheffer@bluemvmt.com
License: MIT
Project-URL: Documentation, https://pyscaffold.org/
Platform: Linux
Classifier: Development Status :: 4 - Beta
Classifier: Programming Language :: Python
License-File: LICENSE.txt
Requires-Dist: importlib-metadata; python_version < "3.8"
Requires-Dist: gsfpy
Requires-Dist: pydantic
Provides-Extra: testing
Requires-Dist: setuptools; extra == "testing"
Requires-Dist: pytest; extra == "testing"
Requires-Dist: pytest-cov; extra == "testing"
